name_generator/__init__.py
name_generator/files/dist.female.name
name_generator/files/dist.female.patronymic
name_generator/files/dist.female.surname
name_generator/files/dist.male.name
name_generator/files/dist.male.patronymic
name_generator/files/dist.male.surname
name_generator/name.py
dtoch_name_generator-0.0.1.dist-info/LICENSE
dtoch_name_generator-0.0.1.dist-info/METADATA
dtoch_name_generator-0.0.1.dist-info/WHEEL
dtoch_name_generator-0.0.1.dist-info/RECORD
